{
  "data": [
    {
      "팀명": "KT",
      "name": "쿠에바스",
      "image": "https://statiz.sporki.com/data/baseball/player/2023/13942.png",
      "ERA": "4.09",
      "G": "19",
      "CG": "0",
      "SHO": "0",
      "W": "5",
      "L": "8",
      "SV": "0",
      "HLD": "0",
      "WPCT": "0.385",
      "TBF": "473",
      "NP": "1834",
      "IP": "112 2/3",
      "H": "98",
      "2B": "21",
      "3B": "2",
      "HR": "12",
      "SAC": "1",
      "SF": "4",
      "BB": "39",
      "IBB": "3",
      "SO": "106",
      "WP": "3",
      "BK": "0",
      "R": "54",
      "ER": "51",
      "BSV": "0",
      "WHIP": "1.22",
      "AVG": "0.230",
      "QS": "3",
      "WAR": "3.27",
      "FIP": "4.21"
    }
  ]
}
